pyvsr53dl/AccessCodes.py
pyvsr53dl/Commands.py
pyvsr53dl/DisplayModes.py
pyvsr53dl/ErrorMessages.py
pyvsr53dl/ThyrCommPackage.py
pyvsr53dl/__init__.py
pyvsr53dl/logger.py
pyvsr53dl/sys.py
pyvsr53dl/vsr53dl.py
pyvsr53dl-0.1.1.dist-info/LICENSE
pyvsr53dl-0.1.1.dist-info/METADATA
pyvsr53dl-0.1.1.dist-info/WHEEL
pyvsr53dl-0.1.1.dist-info/top_level.txt
pyvsr53dl-0.1.1.dist-info/RECORD
