Metadata-Version: 2.1
Name: pyvsr53dl
Version: 0.1.1
Summary: Python Library to interface with Thyracont's VSR53DL Vacuum Sensor through RS458 interface
Home-page: https://github.com/IFAEControl/pyvsr53dl
Author: Oscar Martínez
Author-email: omartinez@ifae.es
License: CC0 1.0 Universal
Platform: UNKNOWN
Classifier: Development Status :: 4 - Beta
Classifier: Programming Language :: Python :: 3
Provides: pyvsr53dl
Requires-Python: >=3
Requires-Dist: pyserial
